[{"id":"ZX00000","name":"Macbook Pro","price":2000,"description":"A brand new state of the art Macbook pro. This computer is great for students, hobbyists and professionals alike."},{"id":"ZX00001","name":"Bluetooth Mouse","price":23,"description":"Control your computer from afar with this wireless bluetooth mouse. At a price this low it's a steal!"},{"id":"ZX00002","name":"Xbox One","price":350,"description":"Get the latest and greatest in gaming consoles. This Xbox One bundles comes with two wireless controllers, two free games and a free month of XBOX Live. The only thing it doesn't come with is all the games on the PS4."},{"id":"ZX00003","name":"mouse pad","price":"24","description":"Never get your mouse stuck on your desk again Buy this pad and rejoin the world with smooth scrolling glory."}]
